Metadata-Version: 2.1
Name: PythonPackageRossic
Version: 0.1
Summary: FinalClass
Home-page: UNKNOWN
Author: rosa
License: UNKNOWN
Platform: UNKNOWN
License-File: license.txt.txt
